twinizer/__init__.py
twinizer/__main__.py
twinizer/cli/__init__.py
twinizer/cli/main.py
twinizer/cli/shell.py
twinizer/cli/commands/__init__.py
twinizer/cli/commands/analyze.py
twinizer/cli/commands/compile.py
twinizer/cli/commands/convert.py
twinizer/cli/commands/debug.py
twinizer/cli/commands/image.py
twinizer/cli/commands/kicad.py
twinizer/cli/commands/kicad_docker.py
twinizer/cli/commands/kicad_with_deps.py
twinizer/cli/commands/software.py
twinizer/cli/commands/test.py
twinizer/code_analyzer/__init__.py
twinizer/code_analyzer/analyzer.py
twinizer/code_analyzer/documentation/__init__.py
twinizer/code_analyzer/documentation/generator.py
twinizer/code_analyzer/linters/__init__.py
twinizer/code_analyzer/linters/cpp.py
twinizer/code_analyzer/linters/javascript.py
twinizer/code_analyzer/linters/python.py
twinizer/converters/__init__.py
twinizer/converters/bin2source.py
twinizer/converters/image2ascii.py
twinizer/converters/kicad2image.py
twinizer/converters/pdf2md.py
twinizer/converters/bin2source/__init__.py
twinizer/converters/bin2source/converters.py
twinizer/converters/image/__init__.py
twinizer/converters/image/ascii.py
twinizer/converters/image/image_to_3d.py
twinizer/converters/image/mermaid/__init__.py
twinizer/converters/image/mermaid/base.py
twinizer/converters/image/mermaid/constants.py
twinizer/converters/image/mermaid/utils.py
twinizer/converters/image/mermaid/converters/__init__.py
twinizer/converters/image/mermaid/converters/html.py
twinizer/converters/image/mermaid/converters/json.py
twinizer/converters/image/mermaid/converters/png.py
twinizer/converters/image/mermaid/diagrams/__init__.py
twinizer/converters/image/mermaid/diagrams/class_diagram.py
twinizer/converters/image/mermaid/diagrams/er.py
twinizer/converters/image/mermaid/diagrams/flowchart.py
twinizer/converters/image/mermaid/diagrams/gantt.py
twinizer/converters/image/mermaid/diagrams/journey.py
twinizer/converters/image/mermaid/diagrams/pie.py
twinizer-0.1.18.dist-info/licenses/LICENSE
twinizer-0.1.18.dist-info/METADATA
twinizer-0.1.18.dist-info/WHEEL
twinizer-0.1.18.dist-info/entry_points.txt
twinizer-0.1.18.dist-info/top_level.txt
twinizer-0.1.18.dist-info/RECORD
