Metadata-Version: 2.4
Name: twinizer
Version: 0.1.18
Summary: A comprehensive environment for hardware and firmware reverse engineering, analysis and management
Author-email: Your Name <your.email@example.com>
License: MIT
Project-URL: Homepage, https://github.com/yourusername/twinizer
Project-URL: Bug Tracker, https://github.com/yourusername/twinizer/issues
Classifier: Development Status :: 3 - Alpha
Classifier: Intended Audience :: Developers
Classifier: Topic :: Software Development :: Embedded Systems
Classifier: License :: OSI Approved :: MIT License
Classifier: Programming Language :: Python :: 3
Classifier: Programming Language :: Python :: 3.9
Requires-Python: >=3.9
License-File: LICENSE
Requires-Dist: prompt-toolkit>=3.0.0
Requires-Dist: click>=8.0.0
Requires-Dist: rich>=10.0.0
Requires-Dist: pyelftools>=0.27
Requires-Dist: capstone>=4.0.2
Requires-Dist: pefile>=2022.5.30
Requires-Dist: decompyle3>=3.9.0
Requires-Dist: pybind11>=2.10.0
Requires-Dist: pdfalyzer>=0.9.0
Requires-Dist: pdf2image>=1.16.0
Requires-Dist: pdfminer.six>=20221105
Requires-Dist: pypdf>=3.5.0
Requires-Dist: python-magic>=0.4.27
Requires-Dist: opencv-python>=4.5.0
Requires-Dist: pytesseract>=0.3.10
Requires-Dist: pillow>=9.0.0
Requires-Dist: jinja2>=3.0.0
Requires-Dist: platformio>=6.1.6
Requires-Dist: pymupdf>=1.20.2
Requires-Dist: ctypesgen>=1.1.1
Requires-Dist: pyyaml>=6.0
Provides-Extra: dev
Requires-Dist: pytest>=7.0.0; extra == "dev"
Requires-Dist: pytest-benchmark>=4.0.0; extra == "dev"
Requires-Dist: memory-profiler>=0.61.0; extra == "dev"
Requires-Dist: black>=23.0.0; extra == "dev"
Requires-Dist: isort>=5.12.0; extra == "dev"
Requires-Dist: flake8>=6.0.0; extra == "dev"
Dynamic: license-file
